cana/__init__.py
cana/base.py
cana/boolean_network.py
cana/boolean_node.py
cana/cutils.c
cana/cutils.cpython-37m-darwin.so
cana/cutils.pyx
cana/random_boolean_network.py
cana/utils.py
cana/bns/__init__.py
cana/canalization/__init__.py
cana/canalization/boolean_canalization.py
cana/canalization/cboolean_canalization.c
cana/canalization/cboolean_canalization.cpython-37m-darwin.so
cana/canalization/cboolean_canalization.pyx
cana/control/__init__.py
cana/control/fvs.py
cana/control/mds.py
cana/control/sc.py
cana/datasets/__init__.py
cana/datasets/bio.py
cana/datasets/bools.py
cana/datasets/breast_cancer.txt
cana/datasets/drosophila_single_cell.txt
cana/datasets/leukemia.txt
cana/datasets/marques-pita_rocha.txt
cana/datasets/motifs.py
cana/datasets/thaliana.txt
cana/datasets/yeast_cell_cycle.txt
cana/datasets/bns/arabidopsis.cnet
cana/datasets/bns/budding_yeast.cnet
cana/datasets/bns/drosophila4.cnet
cana/datasets/bns/fission_yeast.cnet
cana/datasets/bns/mammalian.cnet
cana/datasets/bns/tcr.cnet
cana/datasets/bns/thelper.cnet
cana/datasets/cell_collective/Apoptosis Network.txt
cana/datasets/cell_collective/Arabidopsis thaliana Cell Cycle.txt
cana/datasets/cell_collective/Aurora Kinase A in Neuroblastoma.txt
cana/datasets/cell_collective/B bronchiseptica and T retortaeformis coinfection.txt
cana/datasets/cell_collective/B cell differentiation.txt
cana/datasets/cell_collective/BT474 Breast Cell Line Long-term ErbB Network.txt
cana/datasets/cell_collective/BT474 Breast Cell Line Short-term ErbB Network.txt
cana/datasets/cell_collective/Bordetella bronchiseptica.txt
cana/datasets/cell_collective/Bortezomib Responses in U266 Human Myeloma Cells.txt
cana/datasets/cell_collective/Budding Yeast Cell Cycle 2009.txt
cana/datasets/cell_collective/Budding Yeast Cell Cycle.txt
cana/datasets/cell_collective/CD4 T cell signaling.txt
cana/datasets/cell_collective/CD4+ T Cell Differentiation and Plasticity.txt
cana/datasets/cell_collective/CD4+ T cell Differentiation.txt
cana-0.1.2.dist-info/LICENSE
cana-0.1.2.dist-info/METADATA
cana-0.1.2.dist-info/WHEEL
cana-0.1.2.dist-info/top_level.txt
cana-0.1.2.dist-info/RECORD
